jellyfin/__init__.py
jellyfin/api.py
jellyfin/base.py
jellyfin/generated/__init__.py
jellyfin/generated/api_10_10/__init__.py
jellyfin/generated/api_10_10/api/__init__.py
jellyfin/generated/api_10_10/api/activity_log_api.py
jellyfin/generated/api_10_10/api/api_key_api.py
jellyfin/generated/api_10_10/api/artists_api.py
jellyfin/generated/api_10_10/api/audio_api.py
jellyfin/generated/api_10_10/api/branding_api.py
jellyfin/generated/api_10_10/api/channels_api.py
jellyfin/generated/api_10_10/api/client_log_api.py
jellyfin/generated/api_10_10/api/collection_api.py
jellyfin/generated/api_10_10/api/configuration_api.py
jellyfin/generated/api_10_10/api/dashboard_api.py
jellyfin/generated/api_10_10/api/devices_api.py
jellyfin/generated/api_10_10/api/display_preferences_api.py
jellyfin/generated/api_10_10/api/dynamic_hls_api.py
jellyfin/generated/api_10_10/api/environment_api.py
jellyfin/generated/api_10_10/api/filter_api.py
jellyfin/generated/api_10_10/api/genres_api.py
jellyfin/generated/api_10_10/api/hls_segment_api.py
jellyfin/generated/api_10_10/api/image_api.py
jellyfin/generated/api_10_10/api/instant_mix_api.py
jellyfin/generated/api_10_10/api/item_lookup_api.py
jellyfin/generated/api_10_10/api/item_refresh_api.py
jellyfin/generated/api_10_10/api/item_update_api.py
jellyfin/generated/api_10_10/api/items_api.py
jellyfin/generated/api_10_10/api/library_api.py
jellyfin/generated/api_10_10/api/library_structure_api.py
jellyfin/generated/api_10_10/api/live_tv_api.py
jellyfin/generated/api_10_10/api/localization_api.py
jellyfin/generated/api_10_10/api/lyrics_api.py
jellyfin/generated/api_10_10/api/media_info_api.py
jellyfin/generated/api_10_10/api/media_segments_api.py
jellyfin/generated/api_10_10/api/movies_api.py
jellyfin/generated/api_10_10/api/music_genres_api.py
jellyfin/generated/api_10_10/api/package_api.py
jellyfin/generated/api_10_10/api/persons_api.py
jellyfin/generated/api_10_10/api/playlists_api.py
jellyfin/generated/api_10_10/api/playstate_api.py
jellyfin_sdk-0.3.0.dist-info/WHEEL
jellyfin_sdk-0.3.0.dist-info/METADATA
jellyfin_sdk-0.3.0.dist-info/RECORD
