Metadata-Version: 2.3
Name: jellyfin-sdk
Version: 0.3.0
Summary: A Python SDK for Jellyfin.
Keywords: api,sdk,jellyfin,dataclass,openapi,wrapper-api
Author: Webysther Sperandio
Author-email: Webysther Sperandio <webysther@gmail.com>
License: MPL-2.0
Requires-Dist: urllib3>=2.1.0,<3.0.0
Requires-Dist: python-dateutil>=2.8.2
Requires-Dist: aiohttp>=3.8.4
Requires-Dist: aiohttp-retry>=2.8.3
Requires-Dist: pydantic>=2
Requires-Dist: typing-extensions>=4.7.1
Requires-Dist: lazy-imports>=1,<2
Requires-Dist: httpx>=0.24.1,<1.0.0
Requires-Dist: httpx-oauth>=0.6.0,<1.0.0
Requires-Dist: websockets>=11.0.3,<12.0.0
Requires-Dist: distro>=1.9.0
Requires-Dist: requests>=2.32.5
Requires-Dist: rich>=14.1.0
Requires-Dist: jellyfin-apiclient-python ; extra == 'legacy'
Requires-Python: >=3.10
Project-URL: Documentation, https://webysther.github.io/jellyfin-sdk-python.github.io
Project-URL: GitHub, https://github.com/webysther/jellyfin-sdk-python
Provides-Extra: legacy
